MANIFEST.in
README.md
setup.py
iterable_queue/__init__.py
iterable_queue/example.py
iterable_queue/iq.py
iterable_queue/test.py
iterable_queue.egg-info/PKG-INFO
iterable_queue.egg-info/SOURCES.txt
iterable_queue.egg-info/dependency_links.txt
iterable_queue.egg-info/pbr.json
iterable_queue.egg-info/requires.txt
iterable_queue.egg-info/top_level.txt