Metadata-Version: 1.1
Name: iterable-queue
Version: 1.2.2
Summary: A queue for python that feels like an iterable and knows when its producers are finished
Home-page: https://github.com/enewe101/iterable_queue
Author: Edward Newell
Author-email: edward.newell@gmail.com
License: MIT
Keywords: threading multiprocessing scheduling batch processing queue queueing
Platform: UNKNOWN
Classifier: Development Status :: 3 - Alpha
Classifier: Intended Audience :: Developers
Classifier: Topic :: Software Development :: Build Tools
Classifier: License :: OSI Approved :: MIT License
Classifier: Programming Language :: Python :: 2
Classifier: Programming Language :: Python :: 3
